driink/__init__.py
driink/alembic/README
driink/alembic/env.py
driink/alembic/script.py.mako
driink/alembic/versions/ee07ac805ca9_initial_migration_for_waterlog.py
driink/alembic.ini
driink/applet.py
driink/cli.py
driink/config.py
driink/db.py
driink/driink.ini
driink/gui-resources/water.png
driink/migrations.py
driink/models.py
driink/notifier.py
driink/visualizations.py
driink-0.0.1.dev2.dist-info/LICENSE
driink-0.0.1.dev2.dist-info/METADATA
driink-0.0.1.dev2.dist-info/WHEEL
driink-0.0.1.dev2.dist-info/entry_points.txt
driink-0.0.1.dev2.dist-info/RECORD
