Metadata-Version: 2.1
Name: driink
Version: 0.0.1.dev2
Summary: A lightweight command-line tool to track daily water consumption and send reminders to stay hydrated
Home-page: https://github.com/gaccardo/driink
License: GNU GENERAL PUBLIC LICENSE Version 3
Author: Guido Accardo
Author-email: gaccardo@gmail.com
Requires-Python: >=3.11,<4.0
Classifier: License :: Other/Proprietary License
Classifier: Programming Language :: Python :: 3
Classifier: Programming Language :: Python :: 3.11
Requires-Dist: alembic (>=1.14.0,<2.0.0)
Requires-Dist: click (>=8.1.8,<9.0.0)
Requires-Dist: dbus-python (>=1.3.2,<2.0.0)
Requires-Dist: notify2 (>=0.3.1,<0.4.0)
Requires-Dist: pygobject (>=3.50.0,<4.0.0)
Requires-Dist: sqlalchemy (>=2.0.36,<3.0.0)
Requires-Dist: terminaltables (>=3.1.10,<4.0.0)
Requires-Dist: tqdm (>=4.67.1,<5.0.0)
Project-URL: Repository, https://github.com/gaccardo/driink
